farmos_ext/__init__.py
farmos_ext/area.py
farmos_ext/asset.py
farmos_ext/cli/__init__.py
farmos_ext/cli/output.py
farmos_ext/cli/prompt.py
farmos_ext/farm.py
farmos_ext/farmobj.py
farmos_ext/file.py
farmos_ext/log.py
farmos_ext/others.py
farmos_ext/plan.py
farmos_ext/reporting/__init__.py
farmos_ext/reporting/report.py
farmos_ext/reporting/rstreport.py
farmos_ext/sensor.py
farmos_ext/term.py
farmos_ext-0.1.0.dist-info/LICENSE
farmos_ext-0.1.0.dist-info/WHEEL
farmos_ext-0.1.0.dist-info/METADATA
farmos_ext-0.1.0.dist-info/RECORD
