Metadata-Version: 2.1
Name: farmos-ext
Version: 0.1.0
Summary: 
License: MIT
Author: Lucas Brendel
Author-email: lucasbrendel@gmail.com
Requires-Python: >=3.7,<4.0
Classifier: License :: OSI Approved :: MIT License
Classifier: Programming Language :: Python :: 3
Classifier: Programming Language :: Python :: 3.7
Classifier: Programming Language :: Python :: 3.8
Classifier: Programming Language :: Python :: 3.9
Requires-Dist: colorama (>=0.4.4,<0.5.0)
Requires-Dist: farmOS (>=0.2.0,<0.3.0)
Requires-Dist: prompt-toolkit (>=3.0.16,<4.0.0)
